besbox/__init__.py
besbox/core.py
besbox-0.1.0.dist-info/METADATA
besbox-0.1.0.dist-info/WHEEL
besbox-0.1.0.dist-info/RECORD
