Metadata-Version: 2.4
Name: besbox
Version: 0.1.0
Summary: A library of utilities
Project-URL: Homepage, https://github.com/besartshyti/besbox
Project-URL: Repository, https://github.com/besartshyti/besbox
Author-email: besartshyti <your.email@example.com>
License: MIT
Classifier: Development Status :: 3 - Alpha
Classifier: Intended Audience :: Developers
Classifier: License :: OSI Approved :: MIT License
Classifier: Programming Language :: Python :: 3
Classifier: Programming Language :: Python :: 3.8
Classifier: Programming Language :: Python :: 3.9
Classifier: Programming Language :: Python :: 3.10
Classifier: Programming Language :: Python :: 3.11
Classifier: Programming Language :: Python :: 3.12
Requires-Python: >=3.8
